cgpa_calculator/__init__.py
cgpa_calculator/cgpa_calc.py
cgpa_calculator-2.2.0.dist-info/METADATA
cgpa_calculator-2.2.0.dist-info/WHEEL
cgpa_calculator-2.2.0.dist-info/top_level.txt
cgpa_calculator-2.2.0.dist-info/RECORD
