Metadata-Version: 2.1
Name: cgpa-calculator
Version: 2.2.0
Summary: A Python-based CGPA Calculator to manage courses and calculate weighted CGPA.
Home-page: https://github.com/Mustakim-Taki/cgpa_calculator
Author: S.M.Abrar Mustakim Taki
Author-email: abrar.mustakim@bjitacademy.com
License: UNKNOWN
Platform: UNKNOWN
Classifier: Programming Language :: Python :: 3
Classifier: License :: OSI Approved :: MIT License
Classifier: Operating System :: OS Independent
Requires-Python: >=3.6
